[
  {
    "name": "Альфа Центавра 1119",
    "constellation": "Овен",
    "spectral_class": "G4P",
    "radius": 857501624,
    "rotation": 388.76,
    "age": 2.39,
    "distance": 6493774.9,
    "absolute_magnitude": 1.0
  },
  {
    "name": "Альфа Центавра 4494",
    "constellation": "Стрелец",
    "spectral_class": "O1D",
    "radius": 125459859,
    "rotation": 682.18,
    "age": 0.78,
    "distance": 240760.31,
    "absolute_magnitude": 1.0
  },
  {
    "name": "Альфа Центавра 6818",
    "constellation": "Близнецы",
    "spectral_class": "E6S",
    "radius": 215800742,
    "rotation": 593.25,
    "age": 0.1,
    "distance": 6042395.82,
    "absolute_magnitude": 1.04
  },
  {
    "name": "Альфа Центавра 7537",
    "constellation": "Водолей",
    "spectral_class": "Z4T",
    "radius": 579538605,
    "rotation": 741.8,
    "age": 2.04,
    "distance": 1428433.56,
    "absolute_magnitude": 1.06
  },
  {
    "name": "Альфа Центавра 2224",
    "constellation": "Скорпион",
    "spectral_class": "W4Z",
    "radius": 318858783,
    "rotation": 535.24,
    "age": 2.4,
    "distance": 6634987.13,
    "absolute_magnitude": 1.08
  },
  {
    "name": "Вега 3478",
    "constellation": "Стрелец",
    "spectral_class": "H6L",
    "radius": 184494662,
    "rotation": 399.78,
    "age": 2.63,
    "distance": 7774462.99,
    "absolute_magnitude": 1.1
  },
  {
    "name": "Альфа Центавра 2541",
    "constellation": "Весы",
    "spectral_class": "Y3G",
    "radius": 621210561,
    "rotation": 122.06,
    "age": 1.55,
    "distance": 5061961.71,
    "absolute_magnitude": 1.18
  },
  {
    "name": "Альфа Центавра 6548",
    "constellation": "Рыбы",
    "spectral_class": "J8I",
    "radius": 317612692,
    "rotation": 770.42,
    "age": 1.0,
    "distance": 4247893.71,
    "absolute_magnitude": 1.19
  },
  {
    "name": "Фомалхаут 9625",
    "constellation": "Стрелец",
    "spectral_class": "T6T",
    "radius": 695799671,
    "rotation": 201.85,
    "age": 1.53,
    "distance": 6892964.7,
    "absolute_magnitude": 1.2
  },
  {
    "name": "Бетельгейзе 7050",
    "constellation": "Овен",
    "spectral_class": "A1J",
    "radius": 530590118,
    "rotation": 222.14,
    "age": 0.34,
    "distance": 4966836.81,
    "absolute_magnitude": 1.25
  },
  {
    "name": "Вега 5260",
    "constellation": "Овен",
    "spectral_class": "D5O",
    "radius": 845557904,
    "rotation": 435.37,
    "age": 2.54,
    "distance": 1872076.89,
    "absolute_magnitude": 1.27
  },
  {
    "name": "Вега 3091",
    "constellation": "Козерог",
    "spectral_class": "W7Q",
    "radius": 701092045,
    "rotation": 847.43,
    "age": 2.87,
    "distance": 4117502.92,
    "absolute_magnitude": 1.3
  },
  {
    "name": "Бетельгейзе 4727",
    "constellation": "Стрелец",
    "spectral_class": "A3Z",
    "radius": 870552491,
    "rotation": 732.06,
    "age": 0.71,
    "distance": 1162151.45,
    "absolute_magnitude": 1.3
  },
  {
    "name": "Вега 5250",
    "constellation": "Дева",
    "spectral_class": "M0K",
    "radius": 102416828,
    "rotation": 438.95,
    "age": 1.5,
    "distance": 7124788.92,
    "absolute_magnitude": 1.33
  },
  {
    "name": "Фомальгаут 5064",
    "constellation": "Козерог",
    "spectral_class": "A9N",
    "radius": 291263428,
    "rotation": 565.65,
    "age": 0.04,
    "distance": 8489746.32,
    "absolute_magnitude": 1.4
  },
  {
    "name": "Фомальгаут 6649",
    "constellation": "Близнецы",
    "spectral_class": "I6T",
    "radius": 315414002,
    "rotation": 797.77,
    "age": 0.23,
    "distance": 5589044.48,
    "absolute_magnitude": 1.42
  },
  {
    "name": "Фомальгаут 8709",
    "constellation": "Водолей",
    "spectral_class": "S5B",
    "radius": 430891705,
    "rotation": 626.38,
    "age": 1.38,
    "distance": 273549.37,
    "absolute_magnitude": 1.43
  },
  {
    "name": "Бетельгейзе 7823",
    "constellation": "Близнецы",
    "spectral_class": "I8L",
    "radius": 214633269,
    "rotation": 302.12,
    "age": 0.99,
    "distance": 8309042.07,
    "absolute_magnitude": 1.43
  },
  {
    "name": "Фомалхаут 3744",
    "constellation": "Лев",
    "spectral_class": "S3F",
    "radius": 971047342,
    "rotation": 30.25,
    "age": 2.3,
    "distance": 3273884.59,
    "absolute_magnitude": 1.45
  },
  {
    "name": "Альфа Центавра 1304",
    "constellation": "Рак",
    "spectral_class": "B5R",
    "radius": 914372009,
    "rotation": 193.51,
    "age": 2.98,
    "distance": 8645366.34,
    "absolute_magnitude": 1.53
  },
  {
    "name": "Канопус 2548",
    "constellation": "Рак",
    "spectral_class": "F6L",
    "radius": 941545079,
    "rotation": 933.85,
    "age": 0.02,
    "distance": 2319382.53,
    "absolute_magnitude": 1.56
  },
  {
    "name": "Альфа Центавра 7785",
    "constellation": "Близнецы",
    "spectral_class": "K3T",
    "radius": 385379161,
    "rotation": 457.02,
    "age": 1.25,
    "distance": 2739207.71,
    "absolute_magnitude": 1.57
  },
  {
    "name": "Хадар 4910",
    "constellation": "Телец",
    "spectral_class": "U6L",
    "radius": 492511173,
    "rotation": 990.55,
    "age": 0.79,
    "distance": 2896724.45,
    "absolute_magnitude": 1.58
  },
  {
    "name": "Солнце 3344",
    "constellation": "Весы",
    "spectral_class": "K6V",
    "radius": 881931624,
    "rotation": 473.39,
    "age": 1.97,
    "distance": 4212427.11,
    "absolute_magnitude": 1.65
  },
  {
    "name": "Фомальгаут 9501",
    "constellation": "Телец",
    "spectral_class": "J2X",
    "radius": 211511719,
    "rotation": 711.94,
    "age": 1.7,
    "distance": 2725303.28,
    "absolute_magnitude": 1.67
  },
  {
    "name": "Солнце 5762",
    "constellation": "Скорпион",
    "spectral_class": "V3Y",
    "radius": 91523941,
    "rotation": 391.95,
    "age": 1.4,
    "distance": 8947982.24,
    "absolute_magnitude": 1.69
  },
  {
    "name": "Акрукс 9581",
    "constellation": "Рак",
    "spectral_class": "N0S",
    "radius": 364874810,
    "rotation": 290.95,
    "age": 0.19,
    "distance": 758190.86,
    "absolute_magnitude": 1.7
  },
  {
    "name": "Акрукс 6731",
    "constellation": "Близнецы",
    "spectral_class": "F1X",
    "radius": 744575609,
    "rotation": 735.5,
    "age": 0.13,
    "distance": 4705858.66,
    "absolute_magnitude": 1.79
  },
  {
    "name": "Бетельгейзе 9442",
    "constellation": "Телец",
    "spectral_class": "X9Q",
    "radius": 495373063,
    "rotation": 374.95,
    "age": 0.82,
    "distance": 2564247.68,
    "absolute_magnitude": 1.79
  },
  {
    "name": "Полярная звезда 7672",
    "constellation": "Лев",
    "spectral_class": "Y1G",
    "radius": 531060260,
    "rotation": 490.31,
    "age": 0.97,
    "distance": 5995866.04,
    "absolute_magnitude": 1.96
  },
  {
    "name": "Бетельгейзе 8285",
    "constellation": "Лев",
    "spectral_class": "T8W",
    "radius": 191454203,
    "rotation": 177.79,
    "age": 2.25,
    "distance": 4378087.32,
    "absolute_magnitude": 1.97
  },
  {
    "name": "Антарес 2121",
    "constellation": "Телец",
    "spectral_class": "I0K",
    "radius": 671259767,
    "rotation": 293.49,
    "age": 2.8,
    "distance": 6644543.73,
    "absolute_magnitude": 2.01
  },
  {
    "name": "Солнце 2465",
    "constellation": "Стрелец",
    "spectral_class": "U3B",
    "radius": 418871441,
    "rotation": 730.85,
    "age": 1.93,
    "distance": 5174945.44,
    "absolute_magnitude": 2.05
  },
  {
    "name": "Антарес 7010",
    "constellation": "Козерог",
    "spectral_class": "M0F",
    "radius": 716784964,
    "rotation": 859.62,
    "age": 2.47,
    "distance": 5448394.96,
    "absolute_magnitude": 2.06
  },
  {
    "name": "Антарес 7856",
    "constellation": "Козерог",
    "spectral_class": "B0Q",
    "radius": 286325872,
    "rotation": 738.73,
    "age": 1.09,
    "distance": 4543577.46,
    "absolute_magnitude": 2.07
  },
  {
    "name": "Вега 5736",
    "constellation": "Дева",
    "spectral_class": "J4Q",
    "radius": 620799568,
    "rotation": 280.3,
    "age": 0.12,
    "distance": 2779033.42,
    "absolute_magnitude": 2.15
  },
  {
    "name": "Канопус 4680",
    "constellation": "Рыбы",
    "spectral_class": "N7F",
    "radius": 441800887,
    "rotation": 920.92,
    "age": 1.99,
    "distance": 9405062.12,
    "absolute_magnitude": 2.16
  },
  {
    "name": "Антарес 7539",
    "constellation": "Рак",
    "spectral_class": "D8A",
    "radius": 576886424,
    "rotation": 986.11,
    "age": 0.17,
    "distance": 3479149.28,
    "absolute_magnitude": 2.16
  },
  {
    "name": "Полярная звезда 7136",
    "constellation": "Козерог",
    "spectral_class": "R2U",
    "radius": 625025482,
    "rotation": 147.96,
    "age": 2.0,
    "distance": 3448596.27,
    "absolute_magnitude": 2.21
  },
  {
    "name": "Хадар 2501",
    "constellation": "Скорпион",
    "spectral_class": "V5W",
    "radius": 295780385,
    "rotation": 328.44,
    "age": 2.88,
    "distance": 2289582.28,
    "absolute_magnitude": 2.24
  },
  {
    "name": "Фомалхаут 6598",
    "constellation": "Скорпион",
    "spectral_class": "V5L",
    "radius": 654300084,
    "rotation": 187.46,
    "age": 2.84,
    "distance": 8258745.98,
    "absolute_magnitude": 2.3
  },
  {
    "name": "Полярная звезда 4259",
    "constellation": "Рак",
    "spectral_class": "V7H",
    "radius": 854464616,
    "rotation": 132.7,
    "age": 2.11,
    "distance": 793041.14,
    "absolute_magnitude": 2.3
  },
  {
    "name": "Фомалхаут 5705",
    "constellation": "Водолей",
    "spectral_class": "H7D",
    "radius": 961172656,
    "rotation": 725.08,
    "age": 0.17,
    "distance": 835410.05,
    "absolute_magnitude": 2.31
  },
  {
    "name": "Полярная звезда 1705",
    "constellation": "Рыбы",
    "spectral_class": "U0M",
    "radius": 959872522,
    "rotation": 892.92,
    "age": 2.97,
    "distance": 751033.54,
    "absolute_magnitude": 2.33
  },
  {
    "name": "Антарес 2504",
    "constellation": "Телец",
    "spectral_class": "I9G",
    "radius": 652053403,
    "rotation": 687.06,
    "age": 1.75,
    "distance": 4645751.55,
    "absolute_magnitude": 2.41
  },
  {
    "name": "Акрукс 9843",
    "constellation": "Дева",
    "spectral_class": "N5K",
    "radius": 560121802,
    "rotation": 661.17,
    "age": 0.79,
    "distance": 5643866.28,
    "absolute_magnitude": 2.45
  },
  {
    "name": "Фомалхаут 4628",
    "constellation": "Рак",
    "spectral_class": "X8I",
    "radius": 769902631,
    "rotation": 420.11,
    "age": 0.84,
    "distance": 1160906.91,
    "absolute_magnitude": 2.57
  },
  {
    "name": "Солнце 5907",
    "constellation": "Водолей",
    "spectral_class": "V9W",
    "radius": 825274541,
    "rotation": 545.4,
    "age": 1.66,
    "distance": 8547424.91,
    "absolute_magnitude": 2.58
  },
  {
    "name": "Акрукс 3293",
    "constellation": "Лев",
    "spectral_class": "L7E",
    "radius": 85484900,
    "rotation": 74.9,
    "age": 2.73,
    "distance": 1840059.8,
    "absolute_magnitude": 2.62
  },
  {
    "name": "Ригель 9135",
    "constellation": "Стрелец",
    "spectral_class": "G2O",
    "radius": 996410065,
    "rotation": 198.01,
    "age": 1.13,
    "distance": 1459583.04,
    "absolute_magnitude": 2.65
  },
  {
    "name": "Ригель 2398",
    "constellation": "Водолей",
    "spectral_class": "V0W",
    "radius": 567478334,
    "rotation": 905.82,
    "age": 2.37,
    "distance": 898891.17,
    "absolute_magnitude": 2.7
  },
  {
    "name": "Полярная звезда 6960",
    "constellation": "Лев",
    "spectral_class": "Z7L",
    "radius": 790755012,
    "rotation": 699.88,
    "age": 0.75,
    "distance": 3555625.47,
    "absolute_magnitude": 2.74
  },
  {
    "name": "Полярная звезда 6174",
    "constellation": "Овен",
    "spectral_class": "Z2M",
    "radius": 212802965,
    "rotation": 978.93,
    "age": 0.35,
    "distance": 272377.02,
    "absolute_magnitude": 2.76
  },
  {
    "name": "Полярная звезда 5449",
    "constellation": "Телец",
    "spectral_class": "Y3R",
    "radius": 40391593,
    "rotation": 590.19,
    "age": 2.44,
    "distance": 6312149.08,
    "absolute_magnitude": 2.76
  },
  {
    "name": "Фомальгаут 3982",
    "constellation": "Весы",
    "spectral_class": "B8P",
    "radius": 43478387,
    "rotation": 565.61,
    "age": 1.71,
    "distance": 4365562.6,
    "absolute_magnitude": 2.78
  },
  {
    "name": "Канопус 6590",
    "constellation": "Козерог",
    "spectral_class": "G7O",
    "radius": 824479339,
    "rotation": 981.99,
    "age": 0.68,
    "distance": 9018406.28,
    "absolute_magnitude": 2.84
  },
  {
    "name": "Вега 9950",
    "constellation": "Водолей",
    "spectral_class": "B4G",
    "radius": 169277298,
    "rotation": 777.8,
    "age": 2.73,
    "distance": 1565463.94,
    "absolute_magnitude": 2.87
  },
  {
    "name": "Канопус 5483",
    "constellation": "Стрелец",
    "spectral_class": "W7G",
    "radius": 560460011,
    "rotation": 365.84,
    "age": 2.43,
    "distance": 8816534.75,
    "absolute_magnitude": 2.87
  },
  {
    "name": "Ригель 7176",
    "constellation": "Овен",
    "spectral_class": "T8L",
    "radius": 537789782,
    "rotation": 706.78,
    "age": 2.19,
    "distance": 9781027.69,
    "absolute_magnitude": 2.91
  },
  {
    "name": "Альфа Центавра 3446",
    "constellation": "Рыбы",
    "spectral_class": "U8G",
    "radius": 77844406,
    "rotation": 91.96,
    "age": 0.45,
    "distance": 8518144.75,
    "absolute_magnitude": 2.94
  },
  {
    "name": "Фомальгаут 2479",
    "constellation": "Козерог",
    "spectral_class": "P9O",
    "radius": 551167726,
    "rotation": 111.2,
    "age": 1.79,
    "distance": 7715213.27,
    "absolute_magnitude": 2.97
  },
  {
    "name": "Вега 9381",
    "constellation": "Рыбы",
    "spectral_class": "I5T",
    "radius": 414232958,
    "rotation": 657.69,
    "age": 2.71,
    "distance": 9390700.82,
    "absolute_magnitude": 2.98
  },
  {
    "name": "Хадар 9635",
    "constellation": "Весы",
    "spectral_class": "S8J",
    "radius": 654828445,
    "rotation": 300.74,
    "age": 2.39,
    "distance": 8178078.96,
    "absolute_magnitude": 3.16
  },
  {
    "name": "Фомальгаут 2272",
    "constellation": "Скорпион",
    "spectral_class": "V9D",
    "radius": 902084825,
    "rotation": 393.71,
    "age": 2.05,
    "distance": 4566244.42,
    "absolute_magnitude": 3.2
  },
  {
    "name": "Антарес 4038",
    "constellation": "Козерог",
    "spectral_class": "W6H",
    "radius": 228728766,
    "rotation": 700.1,
    "age": 0.69,
    "distance": 1883015.27,
    "absolute_magnitude": 3.21
  },
  {
    "name": "Фомалхаут 9153",
    "constellation": "Стрелец",
    "spectral_class": "B2T",
    "radius": 496021736,
    "rotation": 465.52,
    "age": 2.66,
    "distance": 813054.7,
    "absolute_magnitude": 3.27
  },
  {
    "name": "Альфа Центавра 1766",
    "constellation": "Рак",
    "spectral_class": "Q2A",
    "radius": 135992964,
    "rotation": 402.46,
    "age": 0.67,
    "distance": 7125871.63,
    "absolute_magnitude": 3.31
  },
  {
    "name": "Акрукс 3525",
    "constellation": "Овен",
    "spectral_class": "B4F",
    "radius": 471400357,
    "rotation": 692.15,
    "age": 2.54,
    "distance": 7103090.86,
    "absolute_magnitude": 3.32
  },
  {
    "name": "Ригель 4999",
    "constellation": "Рак",
    "spectral_class": "I8L",
    "radius": 300478264,
    "rotation": 820.83,
    "age": 2.2,
    "distance": 2369830.44,
    "absolute_magnitude": 3.37
  },
  {
    "name": "Солнце 4365",
    "constellation": "Овен",
    "spectral_class": "D8K",
    "radius": 589125300,
    "rotation": 733.14,
    "age": 0.1,
    "distance": 3373244.75,
    "absolute_magnitude": 3.38
  },
  {
    "name": "Хадар 2976",
    "constellation": "Стрелец",
    "spectral_class": "P0C",
    "radius": 106084238,
    "rotation": 853.14,
    "age": 0.43,
    "distance": 8803887.85,
    "absolute_magnitude": 3.43
  },
  {
    "name": "Бетельгейзе 9324",
    "constellation": "Весы",
    "spectral_class": "G0X",
    "radius": 602302141,
    "rotation": 96.46,
    "age": 1.42,
    "distance": 9033339.08,
    "absolute_magnitude": 3.5
  },
  {
    "name": "Акрукс 6657",
    "constellation": "Близнецы",
    "spectral_class": "P6J",
    "radius": 815543320,
    "rotation": 916.99,
    "age": 1.17,
    "distance": 7394181.09,
    "absolute_magnitude": 3.62
  },
  {
    "name": "Альфа Центавра 5199",
    "constellation": "Козерог",
    "spectral_class": "B4F",
    "radius": 237617019,
    "rotation": 305.97,
    "age": 0.31,
    "distance": 3346740.02,
    "absolute_magnitude": 3.65
  },
  {
    "name": "Бетельгейзе 5393",
    "constellation": "Стрелец",
    "spectral_class": "J7R",
    "radius": 28367801,
    "rotation": 980.92,
    "age": 1.49,
    "distance": 2358678.43,
    "absolute_magnitude": 3.66
  },
  {
    "name": "Альфа Центавра 8297",
    "constellation": "Рыбы",
    "spectral_class": "Z7Y",
    "radius": 143602626,
    "rotation": 897.14,
    "age": 2.27,
    "distance": 3043303.97,
    "absolute_magnitude": 3.67
  },
  {
    "name": "Альфа Центавра 4041",
    "constellation": "Скорпион",
    "spectral_class": "R6D",
    "radius": 740383785,
    "rotation": 977.29,
    "age": 2.04,
    "distance": 5149580.98,
    "absolute_magnitude": 3.72
  },
  {
    "name": "Фомалхаут 9576",
    "constellation": "Рыбы",
    "spectral_class": "G1Y",
    "radius": 866051851,
    "rotation": 339.72,
    "age": 0.64,
    "distance": 4848991.2,
    "absolute_magnitude": 3.77
  },
  {
    "name": "Канопус 6279",
    "constellation": "Телец",
    "spectral_class": "Y3O",
    "radius": 862240522,
    "rotation": 495.49,
    "age": 2.43,
    "distance": 8814357.1,
    "absolute_magnitude": 3.77
  },
  {
    "name": "Ригель 2742",
    "constellation": "Рыбы",
    "spectral_class": "I1B",
    "radius": 397153727,
    "rotation": 42.7,
    "age": 2.3,
    "distance": 1888960.89,
    "absolute_magnitude": 3.81
  },
  {
    "name": "Ригель 8182",
    "constellation": "Близнецы",
    "spectral_class": "V6P",
    "radius": 171138110,
    "rotation": 866.94,
    "age": 2.61,
    "distance": 8603782.99,
    "absolute_magnitude": 3.83
  },
  {
    "name": "Ригель 6403",
    "constellation": "Близнецы",
    "spectral_class": "T9F",
    "radius": 5082133,
    "rotation": 405.48,
    "age": 2.52,
    "distance": 9759496.01,
    "absolute_magnitude": 3.84
  },
  {
    "name": "Фомальгаут 1530",
    "constellation": "Овен",
    "spectral_class": "E6Q",
    "radius": 566988264,
    "rotation": 166.0,
    "age": 0.94,
    "distance": 4805364.71,
    "absolute_magnitude": 3.97
  },
  {
    "name": "Альфа Центавра 3683",
    "constellation": "Скорпион",
    "spectral_class": "N9L",
    "radius": 174294298,
    "rotation": 403.01,
    "age": 0.86,
    "distance": 6023122.45,
    "absolute_magnitude": 3.98
  },
  {
    "name": "Фомальгаут 9402",
    "constellation": "Телец",
    "spectral_class": "Y0F",
    "radius": 707984180,
    "rotation": 887.35,
    "age": 0.19,
    "distance": 2102825.14,
    "absolute_magnitude": 4.0
  },
  {
    "name": "Акрукс 2001",
    "constellation": "Весы",
    "spectral_class": "W7P",
    "radius": 430359637,
    "rotation": 359.38,
    "age": 2.51,
    "distance": 1760103.19,
    "absolute_magnitude": 4.03
  },
  {
    "name": "Ригель 3449",
    "constellation": "Весы",
    "spectral_class": "Y9E",
    "radius": 228030092,
    "rotation": 186.42,
    "age": 0.92,
    "distance": 2973466.27,
    "absolute_magnitude": 4.06
  },
  {
    "name": "Альфа Центавра 8478",
    "constellation": "Рыбы",
    "spectral_class": "A2Z",
    "radius": 977377460,
    "rotation": 610.23,
    "age": 1.91,
    "distance": 5971801.79,
    "absolute_magnitude": 4.13
  },
  {
    "name": "Солнце 6665",
    "constellation": "Рак",
    "spectral_class": "D9U",
    "radius": 596315104,
    "rotation": 182.6,
    "age": 0.37,
    "distance": 3652434.35,
    "absolute_magnitude": 4.17
  },
  {
    "name": "Антарес 5283",
    "constellation": "Овен",
    "spectral_class": "O1A",
    "radius": 463940150,
    "rotation": 370.38,
    "age": 0.82,
    "distance": 4928785.52,
    "absolute_magnitude": 4.18
  },
  {
    "name": "Канопус 5454",
    "constellation": "Весы",
    "spectral_class": "K6B",
    "radius": 977471001,
    "rotation": 76.83,
    "age": 1.85,
    "distance": 7901824.51,
    "absolute_magnitude": 4.22
  },
  {
    "name": "Акрукс 4495",
    "constellation": "Козерог",
    "spectral_class": "B2F",
    "radius": 84420774,
    "rotation": 884.71,
    "age": 1.02,
    "distance": 2079095.48,
    "absolute_magnitude": 4.27
  },
  {
    "name": "Солнце 5818",
    "constellation": "Близнецы",
    "spectral_class": "L6K",
    "radius": 307283175,
    "rotation": 230.72,
    "age": 2.65,
    "distance": 4181884.42,
    "absolute_magnitude": 4.27
  },
  {
    "name": "Ригель 9881",
    "constellation": "Овен",
    "spectral_class": "I0T",
    "radius": 474388784,
    "rotation": 258.05,
    "age": 0.11,
    "distance": 6859057.98,
    "absolute_magnitude": 4.28
  },
  {
    "name": "Канопус 8620",
    "constellation": "Водолей",
    "spectral_class": "Y5C",
    "radius": 138392591,
    "rotation": 954.14,
    "age": 2.41,
    "distance": 6071099.63,
    "absolute_magnitude": 4.35
  },
  {
    "name": "Канопус 1981",
    "constellation": "Рыбы",
    "spectral_class": "J7Z",
    "radius": 656054391,
    "rotation": 895.77,
    "age": 1.27,
    "distance": 3288899.32,
    "absolute_magnitude": 4.37
  },
  {
    "name": "Бетельгейзе 4630",
    "constellation": "Лев",
    "spectral_class": "T5I",
    "radius": 722100143,
    "rotation": 909.34,
    "age": 0.97,
    "distance": 5568330.49,
    "absolute_magnitude": 4.37
  },
  {
    "name": "Фомальгаут 7084",
    "constellation": "Скорпион",
    "spectral_class": "W7O",
    "radius": 519710381,
    "rotation": 12.31,
    "age": 0.94,
    "distance": 6676452.36,
    "absolute_magnitude": 4.39
  },
  {
    "name": "Вега 3828",
    "constellation": "Весы",
    "spectral_class": "V3Z",
    "radius": 521732085,
    "rotation": 524.97,
    "age": 0.5,
    "distance": 483775.15,
    "absolute_magnitude": 4.43
  },
  {
    "name": "Фомальгаут 7240",
    "constellation": "Рыбы",
    "spectral_class": "S3W",
    "radius": 318674756,
    "rotation": 476.09,
    "age": 0.53,
    "distance": 9970256.1,
    "absolute_magnitude": 4.47
  },
  {
    "name": "Вега 3651",
    "constellation": "Скорпион",
    "spectral_class": "B3S",
    "radius": 440596949,
    "rotation": 521.64,
    "age": 2.81,
    "distance": 2028954.28,
    "absolute_magnitude": 4.48
  },
  {
    "name": "Антарес 5090",
    "constellation": "Овен",
    "spectral_class": "K2A",
    "radius": 982257976,
    "rotation": 447.6,
    "age": 0.67,
    "distance": 8128002.68,
    "absolute_magnitude": 4.48
  },
  {
    "name": "Хадар 4138",
    "constellation": "Рак",
    "spectral_class": "T8N",
    "radius": 988065283,
    "rotation": 549.57,
    "age": 2.02,
    "distance": 3314636.37,
    "absolute_magnitude": 4.52
  },
  {
    "name": "Хадар 7058",
    "constellation": "Рак",
    "spectral_class": "Y1J",
    "radius": 376182719,
    "rotation": 343.84,
    "age": 2.95,
    "distance": 2752145.75,
    "absolute_magnitude": 4.58
  },
  {
    "name": "Хадар 7644",
    "constellation": "Рак",
    "spectral_class": "Q4H",
    "radius": 756607333,
    "rotation": 979.05,
    "age": 1.48,
    "distance": 9805382.75,
    "absolute_magnitude": 4.58
  },
  {
    "name": "Фомалхаут 8466",
    "constellation": "Дева",
    "spectral_class": "Z0V",
    "radius": 252912153,
    "rotation": 569.13,
    "age": 0.28,
    "distance": 8316825.0,
    "absolute_magnitude": 4.59
  },
  {
    "name": "Фомальгаут 4829",
    "constellation": "Рыбы",
    "spectral_class": "J5P",
    "radius": 927526071,
    "rotation": 702.28,
    "age": 0.12,
    "distance": 4491246.3,
    "absolute_magnitude": 4.62
  },
  {
    "name": "Акрукс 2084",
    "constellation": "Стрелец",
    "spectral_class": "K4G",
    "radius": 632928055,
    "rotation": 429.5,
    "age": 0.13,
    "distance": 3478301.29,
    "absolute_magnitude": 4.65
  },
  {
    "name": "Фомалхаут 2360",
    "constellation": "Весы",
    "spectral_class": "R8Z",
    "radius": 594382124,
    "rotation": 28.65,
    "age": 2.69,
    "distance": 5080626.25,
    "absolute_magnitude": 4.66
  },
  {
    "name": "Фомалхаут 4961",
    "constellation": "Лев",
    "spectral_class": "B0P",
    "radius": 986319224,
    "rotation": 212.78,
    "age": 1.41,
    "distance": 4098008.01,
    "absolute_magnitude": 4.66
  },
  {
    "name": "Бетельгейзе 5225",
    "constellation": "Лев",
    "spectral_class": "Q0V",
    "radius": 136123113,
    "rotation": 32.44,
    "age": 0.24,
    "distance": 9852091.23,
    "absolute_magnitude": 4.73
  },
  {
    "name": "Солнце 9934",
    "constellation": "Водолей",
    "spectral_class": "O2X",
    "radius": 404580954,
    "rotation": 149.98,
    "age": 0.24,
    "distance": 6675197.17,
    "absolute_magnitude": 4.75
  },
  {
    "name": "Бетельгейзе 4444",
    "constellation": "Овен",
    "spectral_class": "J9B",
    "radius": 626664322,
    "rotation": 234.22,
    "age": 2.47,
    "distance": 5146798.89,
    "absolute_magnitude": 4.84
  },
  {
    "name": "Полярная звезда 7656",
    "constellation": "Весы",
    "spectral_class": "O4W",
    "radius": 335065777,
    "rotation": 918.12,
    "age": 0.35,
    "distance": 7501043.36,
    "absolute_magnitude": 4.85
  },
  {
    "name": "Хадар 1253",
    "constellation": "Близнецы",
    "spectral_class": "J4N",
    "radius": 750682457,
    "rotation": 400.17,
    "age": 1.89,
    "distance": 5613871.62,
    "absolute_magnitude": 4.85
  },
  {
    "name": "Полярная звезда 3958",
    "constellation": "Телец",
    "spectral_class": "S2T",
    "radius": 579112877,
    "rotation": 507.91,
    "age": 2.61,
    "distance": 4310818.54,
    "absolute_magnitude": 4.99
  },
  {
    "name": "Хадар 3272",
    "constellation": "Телец",
    "spectral_class": "M4T",
    "radius": 117817098,
    "rotation": 234.17,
    "age": 2.81,
    "distance": 4828142.27,
    "absolute_magnitude": 4.99
  },
  {
    "name": "Альфа Центавра 9244",
    "constellation": "Телец",
    "spectral_class": "U5L",
    "radius": 911038261,
    "rotation": 800.0,
    "age": 0.43,
    "distance": 291901.78,
    "absolute_magnitude": 5.0
  },
  {
    "name": "Фомалхаут 8398",
    "constellation": "Овен",
    "spectral_class": "U2V",
    "radius": 66245491,
    "rotation": 773.35,
    "age": 2.67,
    "distance": 9547719.72,
    "absolute_magnitude": 5.01
  },
  {
    "name": "Канопус 8196",
    "constellation": "Овен",
    "spectral_class": "B6T",
    "radius": 206457738,
    "rotation": 828.94,
    "age": 2.47,
    "distance": 7062491.08,
    "absolute_magnitude": 5.14
  },
  {
    "name": "Альфа Центавра 1969",
    "constellation": "Лев",
    "spectral_class": "P3I",
    "radius": 225300270,
    "rotation": 355.93,
    "age": 1.04,
    "distance": 769766.06,
    "absolute_magnitude": 5.23
  },
  {
    "name": "Канопус 1496",
    "constellation": "Весы",
    "spectral_class": "U8S",
    "radius": 7790358,
    "rotation": 992.96,
    "age": 0.8,
    "distance": 4540395.16,
    "absolute_magnitude": 5.23
  },
  {
    "name": "Вега 9572",
    "constellation": "Дева",
    "spectral_class": "L0R",
    "radius": 782596035,
    "rotation": 33.65,
    "age": 1.03,
    "distance": 7348019.71,
    "absolute_magnitude": 5.23
  },
  {
    "name": "Фомальгаут 2915",
    "constellation": "Телец",
    "spectral_class": "F3B",
    "radius": 167717489,
    "rotation": 720.27,
    "age": 1.71,
    "distance": 48290.47,
    "absolute_magnitude": 5.37
  },
  {
    "name": "Бетельгейзе 5799",
    "constellation": "Козерог",
    "spectral_class": "E0Q",
    "radius": 868166923,
    "rotation": 192.01,
    "age": 2.26,
    "distance": 3333555.77,
    "absolute_magnitude": 5.38
  },
  {
    "name": "Вега 1863",
    "constellation": "Стрелец",
    "spectral_class": "C2V",
    "radius": 183908418,
    "rotation": 504.51,
    "age": 0.51,
    "distance": 7432952.96,
    "absolute_magnitude": 5.39
  },
  {
    "name": "Антарес 5005",
    "constellation": "Стрелец",
    "spectral_class": "T7P",
    "radius": 108922702,
    "rotation": 82.37,
    "age": 2.98,
    "distance": 4347940.28,
    "absolute_magnitude": 5.42
  },
  {
    "name": "Хадар 1020",
    "constellation": "Овен",
    "spectral_class": "E9S",
    "radius": 706850060,
    "rotation": 712.84,
    "age": 2.12,
    "distance": 1031136.29,
    "absolute_magnitude": 5.5
  },
  {
    "name": "Ригель 1137",
    "constellation": "Козерог",
    "spectral_class": "X1H",
    "radius": 219834665,
    "rotation": 305.18,
    "age": 1.03,
    "distance": 9717859.78,
    "absolute_magnitude": 5.56
  },
  {
    "name": "Фомалхаут 6002",
    "constellation": "Скорпион",
    "spectral_class": "S2H",
    "radius": 590908695,
    "rotation": 476.78,
    "age": 2.38,
    "distance": 24383.42,
    "absolute_magnitude": 5.61
  },
  {
    "name": "Вега 5455",
    "constellation": "Весы",
    "spectral_class": "P9V",
    "radius": 58486851,
    "rotation": 938.25,
    "age": 1.38,
    "distance": 6066858.62,
    "absolute_magnitude": 5.65
  },
  {
    "name": "Солнце 4365",
    "constellation": "Рак",
    "spectral_class": "H3T",
    "radius": 16677124,
    "rotation": 583.17,
    "age": 1.49,
    "distance": 6832472.1,
    "absolute_magnitude": 5.69
  },
  {
    "name": "Фомалхаут 7195",
    "constellation": "Стрелец",
    "spectral_class": "M5F",
    "radius": 69329535,
    "rotation": 519.48,
    "age": 2.52,
    "distance": 7887634.65,
    "absolute_magnitude": 5.72
  },
  {
    "name": "Фомалхаут 5144",
    "constellation": "Дева",
    "spectral_class": "W8N",
    "radius": 740197126,
    "rotation": 425.63,
    "age": 2.58,
    "distance": 2268470.16,
    "absolute_magnitude": 5.75
  },
  {
    "name": "Вега 6621",
    "constellation": "Лев",
    "spectral_class": "X0T",
    "radius": 948534645,
    "rotation": 663.35,
    "age": 2.27,
    "distance": 4853733.69,
    "absolute_magnitude": 5.79
  },
  {
    "name": "Альфа Центавра 1655",
    "constellation": "Скорпион",
    "spectral_class": "H7L",
    "radius": 321263904,
    "rotation": 147.76,
    "age": 2.33,
    "distance": 7731757.67,
    "absolute_magnitude": 5.84
  },
  {
    "name": "Альфа Центавра 8517",
    "constellation": "Водолей",
    "spectral_class": "U2K",
    "radius": 513855531,
    "rotation": 414.1,
    "age": 2.1,
    "distance": 1675637.05,
    "absolute_magnitude": 5.84
  },
  {
    "name": "Фомальгаут 5286",
    "constellation": "Дева",
    "spectral_class": "P9N",
    "radius": 947478347,
    "rotation": 728.81,
    "age": 0.51,
    "distance": 3725034.18,
    "absolute_magnitude": 5.84
  },
  {
    "name": "Полярная звезда 4860",
    "constellation": "Рыбы",
    "spectral_class": "S4F",
    "radius": 416495326,
    "rotation": 876.04,
    "age": 1.14,
    "distance": 3478176.07,
    "absolute_magnitude": 5.87
  },
  {
    "name": "Вега 7293",
    "constellation": "Телец",
    "spectral_class": "B0D",
    "radius": 939675474,
    "rotation": 660.1,
    "age": 2.6,
    "distance": 5194540.82,
    "absolute_magnitude": 5.9
  },
  {
    "name": "Фомалхаут 2558",
    "constellation": "Весы",
    "spectral_class": "Q7T",
    "radius": 222225291,
    "rotation": 462.82,
    "age": 0.52,
    "distance": 8563811.87,
    "absolute_magnitude": 6.02
  },
  {
    "name": "Фомалхаут 6700",
    "constellation": "Телец",
    "spectral_class": "F8H",
    "radius": 60247007,
    "rotation": 45.26,
    "age": 0.98,
    "distance": 8798679.62,
    "absolute_magnitude": 6.07
  },
  {
    "name": "Полярная звезда 7751",
    "constellation": "Овен",
    "spectral_class": "Q4Z",
    "radius": 123288814,
    "rotation": 851.91,
    "age": 2.82,
    "distance": 8401147.16,
    "absolute_magnitude": 6.12
  },
  {
    "name": "Бетельгейзе 6394",
    "constellation": "Стрелец",
    "spectral_class": "E9S",
    "radius": 768727546,
    "rotation": 862.82,
    "age": 2.34,
    "distance": 2103743.57,
    "absolute_magnitude": 6.18
  },
  {
    "name": "Фомалхаут 2507",
    "constellation": "Рыбы",
    "spectral_class": "Q1C",
    "radius": 554276138,
    "rotation": 301.4,
    "age": 0.41,
    "distance": 9761400.27,
    "absolute_magnitude": 6.2
  },
  {
    "name": "Альфа Центавра 7671",
    "constellation": "Скорпион",
    "spectral_class": "E0D",
    "radius": 113789120,
    "rotation": 856.79,
    "age": 1.48,
    "distance": 9864430.14,
    "absolute_magnitude": 6.21
  },
  {
    "name": "Фомалхаут 5410",
    "constellation": "Дева",
    "spectral_class": "U3N",
    "radius": 345313251,
    "rotation": 564.29,
    "age": 0.59,
    "distance": 5814235.97,
    "absolute_magnitude": 6.25
  },
  {
    "name": "Акрукс 4038",
    "constellation": "Телец",
    "spectral_class": "B6F",
    "radius": 474840412,
    "rotation": 111.36,
    "age": 1.44,
    "distance": 3940872.39,
    "absolute_magnitude": 6.27
  },
  {
    "name": "Солнце 5215",
    "constellation": "Дева",
    "spectral_class": "Y5A",
    "radius": 594147912,
    "rotation": 931.34,
    "age": 0.28,
    "distance": 732661.51,
    "absolute_magnitude": 6.27
  },
  {
    "name": "Солнце 5677",
    "constellation": "Скорпион",
    "spectral_class": "C6S",
    "radius": 208788263,
    "rotation": 300.25,
    "age": 1.35,
    "distance": 6633209.86,
    "absolute_magnitude": 6.33
  },
  {
    "name": "Канопус 6593",
    "constellation": "Рак",
    "spectral_class": "S9X",
    "radius": 257847262,
    "rotation": 692.99,
    "age": 1.92,
    "distance": 7192109.56,
    "absolute_magnitude": 6.34
  },
  {
    "name": "Полярная звезда 8611",
    "constellation": "Рыбы",
    "spectral_class": "G5H",
    "radius": 352076747,
    "rotation": 259.81,
    "age": 2.15,
    "distance": 9058642.28,
    "absolute_magnitude": 6.36
  },
  {
    "name": "Альфа Центавра 5908",
    "constellation": "Стрелец",
    "spectral_class": "N8L",
    "radius": 525606392,
    "rotation": 282.72,
    "age": 1.11,
    "distance": 1762273.66,
    "absolute_magnitude": 6.37
  },
  {
    "name": "Хадар 8888",
    "constellation": "Стрелец",
    "spectral_class": "C1M",
    "radius": 986904582,
    "rotation": 398.76,
    "age": 2.26,
    "distance": 2462593.97,
    "absolute_magnitude": 6.38
  },
  {
    "name": "Фомалхаут 6836",
    "constellation": "Дева",
    "spectral_class": "U3O",
    "radius": 862898760,
    "rotation": 611.1,
    "age": 2.39,
    "distance": 4559419.16,
    "absolute_magnitude": 6.4
  },
  {
    "name": "Альфа Центавра 6257",
    "constellation": "Овен",
    "spectral_class": "Z8J",
    "radius": 338938331,
    "rotation": 86.7,
    "age": 2.76,
    "distance": 5572643.84,
    "absolute_magnitude": 6.44
  },
  {
    "name": "Канопус 4010",
    "constellation": "Овен",
    "spectral_class": "M2P",
    "radius": 633027004,
    "rotation": 710.43,
    "age": 2.04,
    "distance": 7717240.55,
    "absolute_magnitude": 6.62
  },
  {
    "name": "Ригель 2661",
    "constellation": "Водолей",
    "spectral_class": "D0E",
    "radius": 666613489,
    "rotation": 829.03,
    "age": 1.11,
    "distance": 5484473.44,
    "absolute_magnitude": 6.72
  },
  {
    "name": "Фомальгаут 7712",
    "constellation": "Овен",
    "spectral_class": "U1P",
    "radius": 564368724,
    "rotation": 668.96,
    "age": 1.66,
    "distance": 5299895.89,
    "absolute_magnitude": 6.79
  },
  {
    "name": "Альфа Центавра 1056",
    "constellation": "Лев",
    "spectral_class": "V5E",
    "radius": 564842138,
    "rotation": 268.97,
    "age": 2.5,
    "distance": 2926023.64,
    "absolute_magnitude": 6.8
  },
  {
    "name": "Бетельгейзе 2142",
    "constellation": "Весы",
    "spectral_class": "S5O",
    "radius": 845298928,
    "rotation": 294.46,
    "age": 1.54,
    "distance": 7427789.73,
    "absolute_magnitude": 6.84
  },
  {
    "name": "Альфа Центавра 4321",
    "constellation": "Близнецы",
    "spectral_class": "Q2Y",
    "radius": 80502942,
    "rotation": 462.36,
    "age": 2.41,
    "distance": 6772231.85,
    "absolute_magnitude": 6.93
  },
  {
    "name": "Канопус 5010",
    "constellation": "Скорпион",
    "spectral_class": "A8P",
    "radius": 768131062,
    "rotation": 124.17,
    "age": 1.73,
    "distance": 7070939.2,
    "absolute_magnitude": 6.96
  },
  {
    "name": "Ригель 4179",
    "constellation": "Рак",
    "spectral_class": "D9P",
    "radius": 221067687,
    "rotation": 26.33,
    "age": 0.17,
    "distance": 9091302.73,
    "absolute_magnitude": 6.97
  },
  {
    "name": "Полярная звезда 2323",
    "constellation": "Телец",
    "spectral_class": "M9R",
    "radius": 188406271,
    "rotation": 270.73,
    "age": 1.79,
    "distance": 9324680.6,
    "absolute_magnitude": 6.98
  },
  {
    "name": "Полярная звезда 4458",
    "constellation": "Телец",
    "spectral_class": "S8J",
    "radius": 505067445,
    "rotation": 259.58,
    "age": 2.79,
    "distance": 2172587.84,
    "absolute_magnitude": 7.12
  },
  {
    "name": "Хадар 7095",
    "constellation": "Водолей",
    "spectral_class": "S5H",
    "radius": 807202735,
    "rotation": 899.87,
    "age": 1.28,
    "distance": 4919505.85,
    "absolute_magnitude": 7.13
  },
  {
    "name": "Хадар 1244",
    "constellation": "Овен",
    "spectral_class": "S9J",
    "radius": 284617393,
    "rotation": 683.41,
    "age": 2.29,
    "distance": 9875412.02,
    "absolute_magnitude": 7.22
  },
  {
    "name": "Бетельгейзе 4697",
    "constellation": "Близнецы",
    "spectral_class": "U4H",
    "radius": 900661586,
    "rotation": 566.92,
    "age": 0.91,
    "distance": 7150391.54,
    "absolute_magnitude": 7.24
  },
  {
    "name": "Ригель 7110",
    "constellation": "Овен",
    "spectral_class": "X3S",
    "radius": 177154029,
    "rotation": 331.39,
    "age": 1.99,
    "distance": 9862368.56,
    "absolute_magnitude": 7.25
  },
  {
    "name": "Акрукс 3656",
    "constellation": "Близнецы",
    "spectral_class": "R9V",
    "radius": 869519701,
    "rotation": 622.45,
    "age": 2.87,
    "distance": 4436371.33,
    "absolute_magnitude": 7.27
  },
  {
    "name": "Хадар 7700",
    "constellation": "Рыбы",
    "spectral_class": "F1N",
    "radius": 443001126,
    "rotation": 817.37,
    "age": 2.06,
    "distance": 4293879.51,
    "absolute_magnitude": 7.27
  },
  {
    "name": "Фомалхаут 1571",
    "constellation": "Близнецы",
    "spectral_class": "Q1T",
    "radius": 559811984,
    "rotation": 190.93,
    "age": 0.32,
    "distance": 3920471.78,
    "absolute_magnitude": 7.3
  },
  {
    "name": "Канопус 1421",
    "constellation": "Овен",
    "spectral_class": "Q0B",
    "radius": 98576500,
    "rotation": 266.1,
    "age": 1.52,
    "distance": 8850495.23,
    "absolute_magnitude": 7.32
  },
  {
    "name": "Акрукс 1872",
    "constellation": "Скорпион",
    "spectral_class": "B5P",
    "radius": 614546361,
    "rotation": 363.87,
    "age": 1.32,
    "distance": 6746365.74,
    "absolute_magnitude": 7.4
  },
  {
    "name": "Солнце 2896",
    "constellation": "Козерог",
    "spectral_class": "J7B",
    "radius": 560032889,
    "rotation": 854.12,
    "age": 0.05,
    "distance": 8481984.42,
    "absolute_magnitude": 7.44
  },
  {
    "name": "Фомалхаут 5801",
    "constellation": "Водолей",
    "spectral_class": "C6H",
    "radius": 396722250,
    "rotation": 128.96,
    "age": 1.79,
    "distance": 8808541.79,
    "absolute_magnitude": 7.5
  },
  {
    "name": "Вега 3370",
    "constellation": "Скорпион",
    "spectral_class": "R2U",
    "radius": 951518802,
    "rotation": 971.32,
    "age": 2.57,
    "distance": 4324423.61,
    "absolute_magnitude": 7.5
  },
  {
    "name": "Альфа Центавра 6131",
    "constellation": "Дева",
    "spectral_class": "E5X",
    "radius": 492273891,
    "rotation": 101.25,
    "age": 0.77,
    "distance": 2565634.0,
    "absolute_magnitude": 7.53
  },
  {
    "name": "Антарес 8395",
    "constellation": "Рыбы",
    "spectral_class": "H5L",
    "radius": 897610836,
    "rotation": 277.09,
    "age": 1.71,
    "distance": 65621.32,
    "absolute_magnitude": 7.58
  },
  {
    "name": "Альфа Центавра 1453",
    "constellation": "Овен",
    "spectral_class": "N8M",
    "radius": 914772061,
    "rotation": 281.98,
    "age": 0.18,
    "distance": 6927806.97,
    "absolute_magnitude": 7.58
  },
  {
    "name": "Антарес 3719",
    "constellation": "Дева",
    "spectral_class": "S7A",
    "radius": 199973970,
    "rotation": 118.04,
    "age": 1.33,
    "distance": 8196729.72,
    "absolute_magnitude": 7.63
  },
  {
    "name": "Хадар 5589",
    "constellation": "Весы",
    "spectral_class": "O5O",
    "radius": 77398773,
    "rotation": 514.18,
    "age": 1.3,
    "distance": 3289952.51,
    "absolute_magnitude": 7.65
  },
  {
    "name": "Вега 9647",
    "constellation": "Близнецы",
    "spectral_class": "A9K",
    "radius": 10409434,
    "rotation": 533.56,
    "age": 0.22,
    "distance": 5021783.35,
    "absolute_magnitude": 7.72
  },
  {
    "name": "Бетельгейзе 2027",
    "constellation": "Водолей",
    "spectral_class": "D7Z",
    "radius": 532094179,
    "rotation": 622.86,
    "age": 0.09,
    "distance": 8088584.41,
    "absolute_magnitude": 7.77
  },
  {
    "name": "Фомалхаут 3248",
    "constellation": "Близнецы",
    "spectral_class": "Z6V",
    "radius": 359815403,
    "rotation": 417.68,
    "age": 1.17,
    "distance": 4680875.16,
    "absolute_magnitude": 7.79
  },
  {
    "name": "Хадар 3109",
    "constellation": "Рак",
    "spectral_class": "A1C",
    "radius": 771978905,
    "rotation": 208.75,
    "age": 0.57,
    "distance": 1523552.53,
    "absolute_magnitude": 7.87
  },
  {
    "name": "Бетельгейзе 5444",
    "constellation": "Рак",
    "spectral_class": "Q8U",
    "radius": 224559759,
    "rotation": 367.55,
    "age": 2.65,
    "distance": 5916240.95,
    "absolute_magnitude": 7.91
  },
  {
    "name": "Канопус 7955",
    "constellation": "Стрелец",
    "spectral_class": "Z2O",
    "radius": 221197424,
    "rotation": 783.38,
    "age": 2.82,
    "distance": 2737124.86,
    "absolute_magnitude": 7.92
  },
  {
    "name": "Антарес 5018",
    "constellation": "Весы",
    "spectral_class": "O2Z",
    "radius": 91338116,
    "rotation": 341.82,
    "age": 1.14,
    "distance": 5858637.01,
    "absolute_magnitude": 7.93
  },
  {
    "name": "Акрукс 8122",
    "constellation": "Стрелец",
    "spectral_class": "G7S",
    "radius": 385700270,
    "rotation": 782.28,
    "age": 1.85,
    "distance": 3623502.82,
    "absolute_magnitude": 7.98
  },
  {
    "name": "Антарес 4288",
    "constellation": "Стрелец",
    "spectral_class": "Z1B",
    "radius": 565943426,
    "rotation": 650.53,
    "age": 1.54,
    "distance": 1338673.36,
    "absolute_magnitude": 8.05
  },
  {
    "name": "Акрукс 4845",
    "constellation": "Рак",
    "spectral_class": "L1Z",
    "radius": 170971790,
    "rotation": 171.32,
    "age": 1.8,
    "distance": 354492.25,
    "absolute_magnitude": 8.08
  },
  {
    "name": "Ригель 3525",
    "constellation": "Козерог",
    "spectral_class": "L2W",
    "radius": 327139251,
    "rotation": 761.24,
    "age": 1.17,
    "distance": 2865095.57,
    "absolute_magnitude": 8.22
  },
  {
    "name": "Вега 5732",
    "constellation": "Козерог",
    "spectral_class": "U9Z",
    "radius": 618255727,
    "rotation": 105.96,
    "age": 0.48,
    "distance": 1408267.76,
    "absolute_magnitude": 8.29
  },
  {
    "name": "Ригель 2411",
    "constellation": "Близнецы",
    "spectral_class": "V0K",
    "radius": 440903890,
    "rotation": 857.83,
    "age": 2.42,
    "distance": 9512167.66,
    "absolute_magnitude": 8.3
  },
  {
    "name": "Бетельгейзе 1893",
    "constellation": "Скорпион",
    "spectral_class": "J5C",
    "radius": 293621151,
    "rotation": 658.46,
    "age": 0.6,
    "distance": 4906680.81,
    "absolute_magnitude": 8.31
  },
  {
    "name": "Фомальгаут 2311",
    "constellation": "Стрелец",
    "spectral_class": "T3H",
    "radius": 454841106,
    "rotation": 386.29,
    "age": 1.09,
    "distance": 7892470.77,
    "absolute_magnitude": 8.33
  },
  {
    "name": "Акрукс 1575",
    "constellation": "Рак",
    "spectral_class": "A2T",
    "radius": 147239429,
    "rotation": 397.3,
    "age": 2.47,
    "distance": 9177568.08,
    "absolute_magnitude": 8.34
  },
  {
    "name": "Полярная звезда 8845",
    "constellation": "Козерог",
    "spectral_class": "K4O",
    "radius": 948969879,
    "rotation": 45.32,
    "age": 1.15,
    "distance": 963243.5,
    "absolute_magnitude": 8.36
  },
  {
    "name": "Фомалхаут 5571",
    "constellation": "Овен",
    "spectral_class": "O1K",
    "radius": 610590557,
    "rotation": 869.73,
    "age": 0.93,
    "distance": 6782125.03,
    "absolute_magnitude": 8.39
  },
  {
    "name": "Фомалхаут 6737",
    "constellation": "Рыбы",
    "spectral_class": "O1I",
    "radius": 534825730,
    "rotation": 384.76,
    "age": 1.02,
    "distance": 1776650.93,
    "absolute_magnitude": 8.48
  },
  {
    "name": "Альфа Центавра 1884",
    "constellation": "Дева",
    "spectral_class": "T4I",
    "radius": 842221066,
    "rotation": 230.6,
    "age": 2.5,
    "distance": 8567298.85,
    "absolute_magnitude": 8.49
  },
  {
    "name": "Хадар 2760",
    "constellation": "Весы",
    "spectral_class": "Y8Q",
    "radius": 337574391,
    "rotation": 770.67,
    "age": 0.14,
    "distance": 1631520.17,
    "absolute_magnitude": 8.5
  },
  {
    "name": "Акрукс 9332",
    "constellation": "Овен",
    "spectral_class": "F8Q",
    "radius": 605786174,
    "rotation": 595.88,
    "age": 1.48,
    "distance": 8101825.11,
    "absolute_magnitude": 8.5
  },
  {
    "name": "Ригель 9441",
    "constellation": "Лев",
    "spectral_class": "F2C",
    "radius": 797594421,
    "rotation": 935.67,
    "age": 0.71,
    "distance": 6229179.4,
    "absolute_magnitude": 8.59
  },
  {
    "name": "Солнце 5800",
    "constellation": "Весы",
    "spectral_class": "Z9Y",
    "radius": 863228116,
    "rotation": 883.22,
    "age": 2.82,
    "distance": 7894949.13,
    "absolute_magnitude": 8.6
  },
  {
    "name": "Солнце 2502",
    "constellation": "Дева",
    "spectral_class": "D1S",
    "radius": 469259124,
    "rotation": 547.78,
    "age": 1.81,
    "distance": 946787.77,
    "absolute_magnitude": 8.65
  },
  {
    "name": "Акрукс 9251",
    "constellation": "Весы",
    "spectral_class": "N3G",
    "radius": 246128989,
    "rotation": 141.67,
    "age": 0.22,
    "distance": 3572906.8,
    "absolute_magnitude": 8.67
  },
  {
    "name": "Альфа Центавра 7296",
    "constellation": "Лев",
    "spectral_class": "R3L",
    "radius": 455465623,
    "rotation": 560.73,
    "age": 1.19,
    "distance": 4699330.66,
    "absolute_magnitude": 8.72
  },
  {
    "name": "Солнце 3183",
    "constellation": "Рак",
    "spectral_class": "S9C",
    "radius": 451096847,
    "rotation": 149.37,
    "age": 0.78,
    "distance": 326567.27,
    "absolute_magnitude": 8.73
  },
  {
    "name": "Антарес 1159",
    "constellation": "Весы",
    "spectral_class": "L2D",
    "radius": 680241838,
    "rotation": 817.58,
    "age": 0.15,
    "distance": 8994867.59,
    "absolute_magnitude": 8.74
  },
  {
    "name": "Солнце 1078",
    "constellation": "Дева",
    "spectral_class": "S0K",
    "radius": 881487433,
    "rotation": 184.72,
    "age": 1.74,
    "distance": 4171539.25,
    "absolute_magnitude": 8.76
  },
  {
    "name": "Солнце 7729",
    "constellation": "Близнецы",
    "spectral_class": "Y9K",
    "radius": 694515016,
    "rotation": 595.12,
    "age": 0.74,
    "distance": 6831637.56,
    "absolute_magnitude": 8.85
  },
  {
    "name": "Канопус 5364",
    "constellation": "Водолей",
    "spectral_class": "Y2J",
    "radius": 699656951,
    "rotation": 625.26,
    "age": 1.48,
    "distance": 6046729.04,
    "absolute_magnitude": 8.91
  },
  {
    "name": "Ригель 5466",
    "constellation": "Близнецы",
    "spectral_class": "N3K",
    "radius": 377055159,
    "rotation": 522.15,
    "age": 1.88,
    "distance": 5626299.76,
    "absolute_magnitude": 8.91
  },
  {
    "name": "Фомалхаут 1210",
    "constellation": "Овен",
    "spectral_class": "D1R",
    "radius": 875774968,
    "rotation": 55.09,
    "age": 2.71,
    "distance": 4779220.17,
    "absolute_magnitude": 8.94
  },
  {
    "name": "Вега 7075",
    "constellation": "Дева",
    "spectral_class": "P2X",
    "radius": 550502315,
    "rotation": 510.0,
    "age": 0.83,
    "distance": 4705489.28,
    "absolute_magnitude": 8.94
  },
  {
    "name": "Канопус 7093",
    "constellation": "Дева",
    "spectral_class": "E6T",
    "radius": 227933408,
    "rotation": 594.72,
    "age": 0.85,
    "distance": 2537624.47,
    "absolute_magnitude": 9.1
  },
  {
    "name": "Солнце 8851",
    "constellation": "Водолей",
    "spectral_class": "A9U",
    "radius": 752972557,
    "rotation": 173.58,
    "age": 0.66,
    "distance": 7559033.46,
    "absolute_magnitude": 9.15
  },
  {
    "name": "Антарес 3072",
    "constellation": "Весы",
    "spectral_class": "P5Q",
    "radius": 677674400,
    "rotation": 684.46,
    "age": 2.44,
    "distance": 3570498.25,
    "absolute_magnitude": 9.2
  },
  {
    "name": "Фомальгаут 6391",
    "constellation": "Близнецы",
    "spectral_class": "D7P",
    "radius": 170204164,
    "rotation": 970.19,
    "age": 1.06,
    "distance": 6597180.83,
    "absolute_magnitude": 9.23
  },
  {
    "name": "Солнце 4061",
    "constellation": "Телец",
    "spectral_class": "E4Q",
    "radius": 307583683,
    "rotation": 188.45,
    "age": 1.73,
    "distance": 4778804.45,
    "absolute_magnitude": 9.24
  },
  {
    "name": "Солнце 1954",
    "constellation": "Весы",
    "spectral_class": "F8Q",
    "radius": 887356172,
    "rotation": 752.36,
    "age": 0.92,
    "distance": 3992828.11,
    "absolute_magnitude": 9.33
  },
  {
    "name": "Вега 5780",
    "constellation": "Скорпион",
    "spectral_class": "M6O",
    "radius": 414767109,
    "rotation": 908.01,
    "age": 1.78,
    "distance": 6630779.67,
    "absolute_magnitude": 9.36
  },
  {
    "name": "Бетельгейзе 1539",
    "constellation": "Овен",
    "spectral_class": "W8Z",
    "radius": 260300884,
    "rotation": 396.31,
    "age": 2.17,
    "distance": 2457584.91,
    "absolute_magnitude": 9.36
  },
  {
    "name": "Альфа Центавра 6299",
    "constellation": "Близнецы",
    "spectral_class": "F7O",
    "radius": 80094828,
    "rotation": 979.86,
    "age": 0.05,
    "distance": 9596073.97,
    "absolute_magnitude": 9.37
  },
  {
    "name": "Фомалхаут 4035",
    "constellation": "Рак",
    "spectral_class": "T3D",
    "radius": 284238215,
    "rotation": 240.3,
    "age": 1.41,
    "distance": 3505256.95,
    "absolute_magnitude": 9.39
  },
  {
    "name": "Канопус 2460",
    "constellation": "Скорпион",
    "spectral_class": "I6E",
    "radius": 524936984,
    "rotation": 701.15,
    "age": 1.6,
    "distance": 5875659.93,
    "absolute_magnitude": 9.43
  },
  {
    "name": "Хадар 9407",
    "constellation": "Водолей",
    "spectral_class": "X7Y",
    "radius": 823051304,
    "rotation": 466.58,
    "age": 0.86,
    "distance": 9909384.08,
    "absolute_magnitude": 9.45
  },
  {
    "name": "Ригель 6318",
    "constellation": "Рыбы",
    "spectral_class": "Q0D",
    "radius": 398443391,
    "rotation": 791.37,
    "age": 1.62,
    "distance": 3694120.7,
    "absolute_magnitude": 9.46
  },
  {
    "name": "Вега 9882",
    "constellation": "Дева",
    "spectral_class": "F9O",
    "radius": 609825904,
    "rotation": 445.05,
    "age": 1.11,
    "distance": 4896499.13,
    "absolute_magnitude": 9.46
  },
  {
    "name": "Вега 3408",
    "constellation": "Стрелец",
    "spectral_class": "K3H",
    "radius": 670562847,
    "rotation": 329.39,
    "age": 2.15,
    "distance": 5908536.87,
    "absolute_magnitude": 9.51
  },
  {
    "name": "Альфа Центавра 2833",
    "constellation": "Близнецы",
    "spectral_class": "P1N",
    "radius": 606748543,
    "rotation": 661.92,
    "age": 1.45,
    "distance": 9324856.96,
    "absolute_magnitude": 9.52
  },
  {
    "name": "Фомалхаут 7044",
    "constellation": "Телец",
    "spectral_class": "F7C",
    "radius": 179589339,
    "rotation": 131.97,
    "age": 0.24,
    "distance": 3337715.19,
    "absolute_magnitude": 9.52
  },
  {
    "name": "Фомальгаут 3110",
    "constellation": "Рак",
    "spectral_class": "Y9O",
    "radius": 172654313,
    "rotation": 877.19,
    "age": 0.01,
    "distance": 3641508.91,
    "absolute_magnitude": 9.57
  },
  {
    "name": "Антарес 7788",
    "constellation": "Близнецы",
    "spectral_class": "H0E",
    "radius": 656042559,
    "rotation": 904.81,
    "age": 0.1,
    "distance": 6525745.78,
    "absolute_magnitude": 9.6
  },
  {
    "name": "Вега 6663",
    "constellation": "Близнецы",
    "spectral_class": "M6Q",
    "radius": 717197637,
    "rotation": 146.07,
    "age": 2.0,
    "distance": 523259.7,
    "absolute_magnitude": 9.7
  },
  {
    "name": "Фомальгаут 9456",
    "constellation": "Весы",
    "spectral_class": "W8H",
    "radius": 697899705,
    "rotation": 733.3,
    "age": 1.95,
    "distance": 6326940.17,
    "absolute_magnitude": 9.84
  },
  {
    "name": "Антарес 9204",
    "constellation": "Рыбы",
    "spectral_class": "P8X",
    "radius": 765169072,
    "rotation": 846.26,
    "age": 0.71,
    "distance": 4926509.85,
    "absolute_magnitude": 9.87
  },
  {
    "name": "Хадар 2959",
    "constellation": "Козерог",
    "spectral_class": "Y7G",
    "radius": 662376392,
    "rotation": 737.43,
    "age": 2.3,
    "distance": 8292944.38,
    "absolute_magnitude": 9.92
  },
  {
    "name": "Хадар 1794",
    "constellation": "Дева",
    "spectral_class": "J1S",
    "radius": 594434584,
    "rotation": 426.85,
    "age": 0.39,
    "distance": 5279360.53,
    "absolute_magnitude": 9.95
  }
]